magicresult/__init__.py
magicresult/bootstrap.py
magicresult/macro.py
magicresult/magicresult.py
magicresult-0.0.0.dist-info/METADATA
magicresult-0.0.0.dist-info/WHEEL
magicresult-0.0.0.dist-info/top_level.txt
magicresult-0.0.0.dist-info/RECORD
