Metadata-Version: 2.1
Name: magicresult
Version: 0.0.0
Summary: Module providing magic result types via Python macros
Home-page: https://github.com/ddworken/magicresult
Author: David Dworken
Author-email: david@daviddworken.com
License: MIT
Keywords: macro magic bad-ideas
Platform: UNKNOWN
Classifier: Development Status :: 3 - Alpha
Classifier: Intended Audience :: Developers
Classifier: Topic :: Software Development :: Build Tools
Classifier: License :: OSI Approved :: MIT License
Classifier: Programming Language :: Python :: 3
Classifier: Programming Language :: Python :: 3.2
Classifier: Programming Language :: Python :: 3.3
Classifier: Programming Language :: Python :: 3.4
Classifier: Programming Language :: Python :: 3.5
Classifier: Programming Language :: Python :: 3.6
Classifier: Programming Language :: Python :: 3.7
Requires-Dist: astor
